{"stat.chestOpened":6,"stat.useItem.minecraft.stone":51,"stat.mineBlock.minecraft.dispenser":2,"stat.leaveGame":3,"stat.mineBlock.minecraft.yellow_flower":1,"stat.useItem.minecraft.diamond_sword":10,"stat.jump":506,"stat.swimOneCm":6639,"stat.fallOneCm":21724,"stat.climbOneCm":1675,"stat.crouchOneCm":14588,"stat.useItem.minecraft.redstone_torch":45,"stat.mineBlock.minecraft.lever":1,"stat.useItem.minecraft.dirt":42,"achievement.exploreAllBiomes":{"value":0,"progress":["Beach","Ocean","River","Plains","Deep Ocean"]},"stat.useItem.minecraft.sapling":18,"stat.damageTaken":4060,"stat.dispenserInspected":7,"stat.flyOneCm":255551,"stat.mineBlock.minecraft.glass":2,"stat.damageDealt":1460,"stat.useItem.minecraft.wool":4,"stat.timeSinceDeath":20942,"stat.useItem.minecraft.sign":2,"stat.walkOneCm":152385,"stat.playerKills":1,"stat.useItem.minecraft.lever":1,"stat.useItem.minecraft.tnt":120,"stat.useItem.minecraft.yellow_flower":1,"stat.entityKilledBy.Skeleton":1,"stat.mineBlock.minecraft.wool":12,"stat.useItem.minecraft.stained_hardened_clay":2,"stat.mineBlock.minecraft.stained_hardened_clay":6,"stat.sprintOneCm":40775,"stat.entityKilledBy.Enderman":1,"stat.useItem.minecraft.fireworks":51,"stat.mineBlock.minecraft.tnt":7,"stat.useItem.minecraft.flint_and_steel":61,"stat.useItem.minecraft.diamond_pickaxe":16,"stat.useItem.minecraft.dye":55,"stat.entityKilledBy.Creeper":2,"stat.mineBlock.minecraft.waterlily":1,"stat.useItem.minecraft.golden_apple":10,"stat.deaths":10,"stat.drop":50,"stat.playOneMinute":42305,"stat.diveOneCm":60586}